setup.cfg
setup.py
lono/__init__.py
lono/device.py
lono/lonoclient.py
lono.egg-info/PKG-INFO
lono.egg-info/SOURCES.txt
lono.egg-info/dependency_links.txt
lono.egg-info/requires.txt
lono.egg-info/top_level.txt