Metadata-Version: 1.1
Name: lono
Version: 0.0.4
Summary: A python package to interface with the Lono Public API
Home-page: http://make.lono.io
Author: Ryan Gaus
Author-email: ryang@lono.io
License: UNKNOWN
Download-URL: https://github.com/peterldowns/mypackage/tarball/0.1
Keywords: lono,sprinkler,iot,outdoor,rachio,skydrop,water
Platform: UNKNOWN
